optfunc2/__init__.py
optfunc2/parser.py
optfunc2-0.2.6.dist-info/LICENSE.txt
optfunc2-0.2.6.dist-info/METADATA
optfunc2-0.2.6.dist-info/WHEEL
optfunc2-0.2.6.dist-info/RECORD
