Metadata-Version: 2.3
Name: optfunc2
Version: 0.2.6
Summary: Generate command line options and help/tips from function automatically.
License: PyPA
Author: bajeer
Author-email: z-bajeer@yeah.net
Requires-Python: >=3.8,<4.0
Classifier: License :: Other/Proprietary License
Classifier: Programming Language :: Python :: 3
Classifier: Programming Language :: Python :: 3.8
Classifier: Programming Language :: Python :: 3.9
Classifier: Programming Language :: Python :: 3.10
Classifier: Programming Language :: Python :: 3.11
Classifier: Programming Language :: Python :: 3.12
Classifier: Programming Language :: Python :: 3.13
Requires-Dist: docstring-parser (>=0.16,<0.17)
Requires-Dist: prettytable (==3.11.0)
Project-URL: Bug Tracker, https://github.com/yjloong/optfunc2/issues
Project-URL: Homepage, https://github.com/yjloong/optfunc2
